{
  "date": "2026-06-20",
  "news": [
    {
      "title": "美伊和平迈出第一步",
      "summary": "美伊和平协议谈判取得初步进展，双方同意在瑞士举行会谈。伊朗外长将赴瑞士，美国特使正在途中。此前，美情报称以色列政府有意继续对真主党展开行动，可能破坏和平进程。此次和平协议旨在结束持续数月的中东冲突，但细节谈判仍面临诸多挑战，包括黎巴嫩局势、核问题等。协议的成功与否将对中东地缘政治格局产生深远影响。",
      "reason": "国际政治高热度新闻，美伊关系牵动全球能源与安全格局",
      "impact_areas": [
        "政治",
        "地缘",
        "经济金融"
      ],
      "impact_level": "重大",
      "sources": [
        {
          "name": "财新网",
          "url": "https://database.caixin.com/2026-06-20/102455823.html"
        },
        {
          "name": "澎湃新闻",
          "url": "https://m.thepaper.cn/detail/33419499"
        },
        {
          "name": "凤凰网",
          "url": "https://news.ifeng.com/c/8u6WrTf14JE"
        }
      ]
    },
    {
      "title": "AI加剧经济K型分化",
      "summary": "最新研究表明，人工智能技术的快速发展正在加剧经济和就业的K型分化，高技能、高收入群体与低技能、低收入群体之间的差距不断扩大。AI技术正在重塑就业市场，一方面创造高薪技术岗位，另一方面替代大量中低技能工作。专家呼吁政策制定者及早应对，包括加强教育培训、完善社会保障体系、推动普惠性技术发展等措施，以缓解AI带来的社会分化问题。",
      "reason": "科技类新闻，AI对经济和就业结构产生深远影响",
      "impact_areas": [
        "科技",
        "经济金融",
        "社会"
      ],
      "impact_level": "重大",
      "sources": [
        {
          "name": "财新网",
          "url": "https://database.caixin.com/2026-06-20/102455836.html"
        }
      ]
    },
    {
      "title": "AI负荷改变电力运行逻辑",
      "summary": "随着人工智能技术的快速发展，AI算力需求激增对电力系统带来前所未有的挑战。数据显示，大型AI模型训练和运行消耗的电力呈指数级增长，正在改变传统电力系统的运行逻辑。为应对这一挑战，多方正在探索算力与电力的协同机制，包括\"东数海算\"、\"东数西算\"等战略布局，以及发展储能技术以平衡电网负荷。专家表示，AI与电力的协同发展将成为未来能源系统的重要方向。",
      "reason": "科技类新闻，AI与能源协同发展改变能源格局",
      "impact_areas": [
        "科技",
        "能源"
      ],
      "impact_level": "重大",
      "sources": [
        {
          "name": "财新网",
          "url": "https://database.caixin.com/2026-06-20/102455819.html"
        }
      ]
    },
    {
      "title": "金融AI安全新规出台",
      "summary": "监管部门发布最新指导意见，规范银行业和保险业人工智能安全开发应用。新规要求金融机构建立健全AI安全管理制度，加强算法风险管理，确保AI决策的透明度和可解释性。同时，强调保护消费者数据隐私，防范算法歧视和滥用。业内人士表示，这一指导文件的出台将推动金融行业AI应用的健康发展，平衡技术创新与风险防控。",
      "reason": "金融科技监管政策出台，影响行业AI应用方向",
      "impact_areas": [
        "科技",
        "经济金融"
      ],
      "impact_level": "重大",
      "sources": [
        {
          "name": "财新网",
          "url": "https://mini.caixin.com/2026-06-20/102455814.html"
        }
      ]
    },
    {
      "title": "算电协同上海样本",
      "summary": "上海推出\"算电协同\"创新模式，将\"东数海算\"与\"东数西算\"战略相结合，并融入储能技术，打造全国领先的算力与电力协同发展样板。该模式通过优化算力布局，将高耗能计算任务向能源丰富地区转移，同时利用储能技术平衡电网负荷，提高能源利用效率。专家表示，这一模式有望解决AI快速发展带来的能源挑战，为全国算力基础设施建设提供可复制经验。",
      "reason": "科技与能源协同创新，解决AI发展能源挑战",
      "impact_areas": [
        "科技",
        "能源"
      ],
      "impact_level": "重大",
      "sources": [
        {
          "name": "财新网",
          "url": "https://database.caixin.com/2026-06-20/102455821.html"
        }
      ]
    },
    {
      "title": "AI+消费发展提速",
      "summary": "八部门联合印发《实施意见》，明确提出加快发展\"人工智能+消费\"，推动AI技术在消费领域的创新应用。文件强调要支持AI在智能家居、智能穿戴、智能出行等领域的应用，培育新型消费场景；同时加强AI消费产品安全监管，保障消费者权益。业内人士分析，这一政策将加速AI技术与消费市场的深度融合，催生新的经济增长点，但也需警惕数据安全和隐私保护问题。",
      "reason": "政策推动AI与消费融合，创造新经济增长点",
      "impact_areas": [
        "科技",
        "经济金融",
        "社会"
      ],
      "impact_level": "重大",
      "sources": [
        {
          "name": "雪球热帖",
          "url": "https://news.google.com/rss/articles/CBMieEFVX3lxTE9ieTNPdzRvUHRRQnNMOGg5bk96Rl9KNDExUmlJSy1JbjVpbHhoUGtfN215ek5YMVUyczl5d0hZVGZ1WmN4ODVzUFN3X19Qa1RUMXdaZlhnZmo0LVd0REJjSVROTDgwODdHc1JvSnNTckdKa3ZOSkJTNA?oc=5"
        }
      ]
    },
    {
      "title": "AI驱动电力革命",
      "summary": "知名能源专家胡兆光发表观点，认为人工智能技术正在引领电力行业发生革命性变革。AI技术正在优化电网调度、提高新能源消纳能力、预测电力需求、降低能耗等方面发挥关键作用。随着AI与电力系统的深度融合，未来电力系统将更加智能化、高效化、绿色化。专家预测，AI驱动的电力革命将重塑能源行业格局，推动能源结构转型，助力实现\"双碳\"目标。",
      "reason": "AI与能源深度融合，引领电力行业革命",
      "impact_areas": [
        "科技",
        "能源"
      ],
      "impact_level": "重大",
      "sources": [
        {
          "name": "雪球热帖",
          "url": "https://news.google.com/rss/articles/CBMieEFVX3lxTFBpaHN5X3FxLXRta3ZSd2lzZXNoUWFQUTFmVVNibk13RDBzVHBHZnRIMUk3N0Zsc240YXBZWXEzZmgtRXZ0bTRtN1BDeXFvSE94LVFsQWRDQjhmeHpmR0ZvM2EyMzBzQzU0SUhha1hnNllkTi04UzNKRg?oc=5"
        }
      ]
    },
    {
      "title": "以色列或破坏美伊和谈",
      "summary": "据美国情报机构透露，以色列政府有意继续对真主党展开军事行动，这可能破坏正在推进的美伊和平谈判。此前，美伊双方已同意在瑞士举行会谈，寻求结束持续数月的中东冲突。然而，以色列的强硬立场可能使和平进程复杂化。分析人士指出，以色列的行动不仅影响中东局势，还可能牵动全球能源市场，引发国际社会广泛关注。",
      "reason": "中东局势紧张，可能影响全球能源与安全格局",
      "impact_areas": [
        "政治",
        "地缘",
        "经济金融"
      ],
      "impact_level": "重大",
      "sources": [
        {
          "name": "澎湃新闻",
          "url": "https://m.thepaper.cn/detail/33419495"
        }
      ]
    },
    {
      "title": "美伊和平会谈将启",
      "summary": "伊朗外长将赴瑞士参加和平谈判，美国特使正在途中。此次会谈旨在结束持续数月的中东冲突，寻求解决核问题和地区安全挑战。此前，美伊双方已表示愿意通过对话解决分歧，但谈判仍面临诸多挑战。国际社会对此次会谈寄予厚望，认为这是缓解中东紧张局势的重要机会。会谈结果将对全球能源市场、地缘政治格局产生深远影响。",
      "reason": "美伊关键会谈，牵动全球能源与安全格局",
      "impact_areas": [
        "政治",
        "地缘",
        "经济金融"
      ],
      "impact_level": "重大",
      "sources": [
        {
          "name": "澎湃新闻",
          "url": "https://m.thepaper.cn/detail/33419499"
        },
        {
          "name": "凤凰网",
          "url": "https://news.ifeng.com/c/8u6WrTf14JE"
        }
      ]
    },
    {
      "title": "美联储鹰派信号",
      "summary": "美联储释放鹰派政策信号，暗示可能维持高利率更长时间，导致本周金价微涨而银价大跌。市场分析认为，美联储的鹰派立场反映了其对通胀的持续担忧，以及对经济增长韧性的评估。金银比价扩大至多年高位，反映市场对经济前景的分化预期。专家指出，美联储政策走向将继续影响全球金融市场，投资者需密切关注通胀数据和就业市场表现。",
      "reason": "美联储政策信号影响贵金属市场，具有投资参考价值",
      "impact_areas": [
        "经济金融"
      ],
      "impact_level": "重大",
      "sources": [
        {
          "name": "36氪",
          "url": "https://www.36kr.com/newsflashes/3860905883178248"
        }
      ]
    }
  ],
  "total_fetched": 257,
  "generated_at": "2026-06-20T12:28:37.562967+08:00"
}