{
  "date": "2026-05-10",
  "news": [
    {
      "title": "史上最大独角兽关停",
      "summary": "全球估值最高的独角兽企业之一，总估值达1.8万亿美元的公司突然宣布关停。该企业曾被视为科技行业的标杆，其关停将对相关产业链产生深远影响，可能导致数千人失业，并引发投资者对高估值科技企业的重新评估。此次事件也反映了当前科技行业面临的严峻挑战和不确定性。",
      "reason": "史上最大独角兽突然关停，对科技行业和投资市场产生重大冲击",
      "impact_areas": [
        "科技",
        "经济金融"
      ],
      "impact_level": "重大",
      "sources": [
        {
          "name": "雪球热帖",
          "url": "https://news.google.com/rss/articles/CBMidkFVX3lxTFBva0VxaUp5ZDJESUJBd05od0lVRktrYmNfa2pUNHdQdDQ2Q2dVa3A2WTRpa2NRQmZUdS1NTFg3MnlrTWZmWVZXZ08yZy1VMXhLc0U0WUl4blEzNjlDYjNhOTNqX0w0S1EzMllTdmM5WnN1cUNTd3c"
        }
      ]
    },
    {
      "title": "英伟达AI投资超400亿",
      "summary": "英伟达宣布全面布局AI生态系统，今年股权投资规模已超过400亿美元，创下历史新高。该公司正通过战略投资、并购等方式，在AI芯片、软件、应用等多个领域建立完整生态。此举将进一步巩固英伟达在AI领域的领先地位，并对全球AI产业格局产生深远影响，可能加速AI技术在各行业的应用落地。",
      "reason": "英伟达AI生态投资创历史新高，将重塑全球AI产业格局",
      "impact_areas": [
        "科技",
        "经济金融"
      ],
      "impact_level": "重大",
      "sources": [
        {
          "name": "36氪",
          "url": "https://www.36kr.com/newsflashes/3802794581991168"
        }
      ]
    },
    {
      "title": "特斯拉Model S/X停产",
      "summary": "特斯拉宣布已在弗里蒙特工厂生产最后一辆Model S和Model X，标志着这两款经典车型正式停产。特斯拉正将资源集中投向更受欢迎的Model 3和Model Y，以及未来的Cybertruck等新车型。这一战略调整反映了特斯拉产品线的优化方向，可能对豪华电动车市场格局产生深远影响。",
      "reason": "特斯拉经典车型停产，战略重心转向新车型，影响电动车市场格局",
      "impact_areas": [
        "科技",
        "产业"
      ],
      "impact_level": "重大",
      "sources": [
        {
          "name": "36氪",
          "url": "https://www.36kr.com/newsflashes/3802823310188292"
        }
      ]
    },
    {
      "title": "香港IPO同比增604%",
      "summary": "港交所数据显示，2026年前四个月香港IPO市场集资金额达1514亿港元，同比大幅上升604%。这一增长主要得益于大型科技企业和新经济企业的上市热潮。香港作为国际金融中心，其IPO市场的活跃度反映了全球资本流向和投资者信心，对区域经济和金融市场稳定具有重要意义。",
      "reason": "香港IPO市场同比激增604%，反映全球资本流向和投资者信心",
      "impact_areas": [
        "经济金融"
      ],
      "impact_level": "重大",
      "sources": [
        {
          "name": "36氪",
          "url": "https://www.36kr.com/newsflashes/3802791947017732"
        }
      ]
    },
    {
      "title": "普京称俄乌冲突将结束",
      "summary": "俄罗斯总统普京在接受记者采访时表示，俄乌冲突正走向结束。这一表态引发国际社会广泛关注，被视为俄乌局势可能发生重大转折的信号。普京强调，俄罗斯已实现其主要战略目标，并愿意通过政治途径解决剩余问题。这一表态可能对欧洲安全格局、全球能源市场以及国际关系产生深远影响。",
      "reason": "普京称俄乌冲突正走向结束，可能改变欧洲安全格局和全球能源市场",
      "impact_areas": [
        "政治",
        "地缘"
      ],
      "impact_level": "重大",
      "sources": [
        {
          "name": "澎湃新闻",
          "url": "https://m.thepaper.cn/detail/33150290"
        }
      ]
    },
    {
      "title": "普京强调俄中协作重要性",
      "summary": "俄罗斯总统普京强调，俄中协作是维护国际关系稳定的最重要因素。这一表态凸显了俄中关系在全球政治格局中的重要性。普京表示，两国在多个领域有着广泛的共同利益和合作空间，将继续深化全面战略协作伙伴关系。这一表态可能对全球多极化格局、国际秩序以及区域安全产生深远影响。",
      "reason": "普京强调俄中协作对国际关系稳定的关键作用，凸显两国在全球政治格局中的重要性",
      "impact_areas": [
        "政治",
        "地缘"
      ],
      "impact_level": "重大",
      "sources": [
        {
          "name": "澎湃新闻",
          "url": "https://m.thepaper.cn/detail/33149668"
        }
      ]
    },
    {
      "title": "俄乌互相指责违反停火",
      "summary": "俄罗斯指责乌克兰违反停火协议，对俄罗斯领土发动袭击。这一指控加剧了俄乌紧张局势，可能破坏正在进行的和平谈判。俄罗斯表示将采取相应措施回应，而乌克兰则否认这一指控。这一事件对欧洲安全局势、全球能源市场以及国际关系产生重大影响，增加了地区冲突升级的风险。",
      "reason": "俄乌互相指责违反停火协议，加剧地区紧张局势，可能破坏和平进程",
      "impact_areas": [
        "政治",
        "地缘"
      ],
      "impact_level": "重大",
      "sources": [
        {
          "name": "凤凰网",
          "url": "https://news.ifeng.com/c/8t0WrnmFT1n"
        }
      ]
    },
    {
      "title": "俄中油气合作将迈大步",
      "summary": "俄罗斯总统普京宣布，俄中油气领域合作将迈出重大一步。这一表态可能涉及能源供应协议、基础设施建设或技术合作等多个方面。中俄作为全球重要的能源生产国和消费国，深化油气合作将对全球能源格局、地缘政治以及两国经济发展产生深远影响，也可能改变全球能源贸易流向。",
      "reason": "普京宣布俄中油气合作将迈出重大一步，可能改变全球能源格局和贸易流向",
      "impact_areas": [
        "经济金融",
        "地缘"
      ],
      "impact_level": "重大",
      "sources": [
        {
          "name": "凤凰网",
          "url": "https://news.ifeng.com/c/8t0VMfrttCv"
        }
      ]
    },
    {
      "title": "碳酸锂价格迫近20万",
      "summary": "碳酸锂价格持续上涨，吨价已迫近20万元大关，创下近年新高。这一价格上涨主要受新能源汽车需求激增、供应紧张以及投机因素等多重因素推动。随着价格攀升，机构对锂价后市走势出现明显分歧，部分机构认为仍有上涨空间，而另一部分则担忧泡沫风险。锂价波动对新能源汽车产业链、储能行业以及全球能源转型进程产生深远影响。",
      "reason": "碳酸锂价格迫近20万元创近年新高，机构对后市分歧加大，影响新能源产业链",
      "impact_areas": [
        "经济金融",
        "科技"
      ],
      "impact_level": "重大",
      "sources": [
        {
          "name": "财新网",
          "url": "https://database.caixin.com/2026-05-10/102442732.html"
        }
      ]
    },
    {
      "title": "AI投资转向盈利驱动",
      "summary": "公募基金一季报显示，机构对AI板块的投资逻辑已从概念炒作转向盈利驱动。随着AI技术商业化进程加速，越来越多的AI企业开始实现盈利，吸引了机构投资者的关注。这一转变反映了AI产业从概念期向成熟期过渡的趋势，可能对AI板块估值体系、相关企业融资环境以及整个科技投资生态产生深远影响。",
      "reason": "公募基金AI投资逻辑转向盈利驱动，反映AI产业从概念期向成熟期过渡",
      "impact_areas": [
        "经济金融",
        "科技"
      ],
      "impact_level": "重大",
      "sources": [
        {
          "name": "财新网",
          "url": "https://database.caixin.com/2026-05-10/102442721.html"
        }
      ]
    }
  ],
  "total_fetched": 227,
  "generated_at": "2026-05-10T12:28:11.253384+08:00"
}